conditional/__init__.py
conditional/conditional.py
conditional/conditional.pyi
conditional/py.typed
conditional-2.0.dist-info/LICENSE
conditional-2.0.dist-info/METADATA
conditional-2.0.dist-info/WHEEL
conditional-2.0.dist-info/top_level.txt
conditional-2.0.dist-info/RECORD
