Metadata-Version: 2.1
Name: conditional
Version: 2.0
Summary: Conditionally enter a context manager
Home-page: https://github.com/stefanholek/conditional
Author: Stefan H. Holek
Author-email: stefan@epy.co.at
License: BSD-2-Clause
Project-URL: Documentation, https://conditional.readthedocs.io/en/stable/
Keywords: conditional,context manager,contextmanager,with,async,async with,enter,exit
Classifier: Development Status :: 5 - Production/Stable
Classifier: Intended Audience :: Developers
Classifier: License :: OSI Approved :: BSD License
Classifier: Operating System :: OS Independent
Classifier: Programming Language :: Python
Classifier: Programming Language :: Python :: 3
Requires-Python: >=3.5
License-File: LICENSE
Provides-Extra: docs
Requires-Dist: sphinx ==5.3.0 ; extra == 'docs'
Requires-Dist: sphinx-rtd-theme ==1.0.0 ; extra == 'docs'
Provides-Extra: mypy
Requires-Dist: mypy ; extra == 'mypy'
Provides-Extra: testing
Requires-Dist: flexmock ; extra == 'testing'
